{"name":"build-javascript","namedChunkGroups":{"app":{"name":"app","assets":[{"name":"webpack-runtime-46bb2c78a026417abecf.js","size":5112},{"name":"framework-507b50760217d811fd5e.js","size":141469},{"name":"app-3f37fa1802e829bca058.js","size":318701}],"filteredAssets":0,"assetsSize":465282,"filteredAuxiliaryAssets":3,"auxiliaryAssetsSize":1812889},"component---src-pages-404-tsx":{"name":"component---src-pages-404-tsx","assets":[{"name":"component---src-pages-404-tsx-e42d80d7b901399e0346.js","size":4982}],"filteredAssets":0,"assetsSize":4982,"filteredAuxiliaryAssets":1,"auxiliaryAssetsSize":19232},"component---src-pages-index-tsx":{"name":"component---src-pages-index-tsx","assets":[{"name":"component---src-pages-index-tsx-14730b2c9bcba876fc45.js","size":3274}],"filteredAssets":0,"assetsSize":3274,"filteredAuxiliaryAssets":1,"auxiliaryAssetsSize":11001},"component---src-pages-netflix-tsx":{"name":"component---src-pages-netflix-tsx","assets":[{"name":"styles.1bc937e277304e2c702e.css","size":24411},{"name":"1bfc9850-edc70cf807bd54ecfe46.js","size":1031},{"name":"component---src-pages-netflix-tsx-de665177b0dd248a057e.js","size":98934}],"filteredAssets":0,"assetsSize":124376,"filteredAuxiliaryAssets":2,"auxiliaryAssetsSize":1726757}},"assetsByChunkName":{"app":["webpack-runtime-46bb2c78a026417abecf.js","framework-507b50760217d811fd5e.js","app-3f37fa1802e829bca058.js"],"component---src-pages-404-tsx":["component---src-pages-404-tsx-e42d80d7b901399e0346.js"],"component---src-pages-index-tsx":["component---src-pages-index-tsx-14730b2c9bcba876fc45.js"],"component---src-pages-netflix-tsx":["styles.1bc937e277304e2c702e.css","1bfc9850-edc70cf807bd54ecfe46.js","component---src-pages-netflix-tsx-de665177b0dd248a057e.js"]},"childAssetsByChunkName":{}}