{"name":"build-javascript","namedChunkGroups":{"app":{"name":"app","assets":[{"name":"webpack-runtime-d049109ade83f6808415.js","size":5112},{"name":"framework-507b50760217d811fd5e.js","size":141469},{"name":"app-e8af04bbd65b83e790e7.js","size":318422}],"filteredAssets":0,"assetsSize":465003,"filteredAuxiliaryAssets":3,"auxiliaryAssetsSize":1812935},"component---src-pages-404-tsx":{"name":"component---src-pages-404-tsx","assets":[{"name":"component---src-pages-404-tsx-e42d80d7b901399e0346.js","size":4982}],"filteredAssets":0,"assetsSize":4982,"filteredAuxiliaryAssets":1,"auxiliaryAssetsSize":19232},"component---src-pages-index-tsx":{"name":"component---src-pages-index-tsx","assets":[{"name":"component---src-pages-index-tsx-14730b2c9bcba876fc45.js","size":3274}],"filteredAssets":0,"assetsSize":3274,"filteredAuxiliaryAssets":1,"auxiliaryAssetsSize":11001},"component---src-pages-netflix-tsx":{"name":"component---src-pages-netflix-tsx","assets":[{"name":"styles.1bc937e277304e2c702e.css","size":24411},{"name":"1bfc9850-edc70cf807bd54ecfe46.js","size":1031},{"name":"component---src-pages-netflix-tsx-01aacb1365a4ee25a445.js","size":98932}],"filteredAssets":0,"assetsSize":124374,"filteredAuxiliaryAssets":2,"auxiliaryAssetsSize":1726757}},"assetsByChunkName":{"app":["webpack-runtime-d049109ade83f6808415.js","framework-507b50760217d811fd5e.js","app-e8af04bbd65b83e790e7.js"],"component---src-pages-404-tsx":["component---src-pages-404-tsx-e42d80d7b901399e0346.js"],"component---src-pages-index-tsx":["component---src-pages-index-tsx-14730b2c9bcba876fc45.js"],"component---src-pages-netflix-tsx":["styles.1bc937e277304e2c702e.css","1bfc9850-edc70cf807bd54ecfe46.js","component---src-pages-netflix-tsx-01aacb1365a4ee25a445.js"]},"childAssetsByChunkName":{}}